pymeshup/GUI.py
pymeshup/__init__.py
pymeshup/frames.py
pymeshup/ghs_import.py
pymeshup/hull.py
pymeshup/step_import.py
pymeshup/volumes.py
pymeshup/DAVE/GHS_to_DAVE.py
pymeshup/DAVE/GHS_to_DAVE_dialog.py
pymeshup/DAVE/GHS_to_DAVE_form.py
pymeshup/gui/__init__.py
pymeshup/gui/capytaine_runner.py
pymeshup/gui/main.py
pymeshup/gui/digitizer/__init__.py
pymeshup/gui/digitizer/digitizer.py
pymeshup/gui/examples/Rubber Duck.obj
pymeshup/gui/examples/barge_and_tanks_using_dicts_and_functions.pym
pymeshup/gui/examples/barge_mesh_from_box.pym
pymeshup/gui/examples/cheetah.stl
pymeshup/gui/examples/create tank in a given hull-shape.pym
pymeshup/gui/examples/make diffraction mesh.pym
pymeshup/gui/examples/pontoon from frames.pym
pymeshup/gui/examples/sailboat.pym
pymeshup/gui/examples/simple.pym
pymeshup/gui/forms/__init__.py
pymeshup/gui/forms/main_form.py
pymeshup/gui/helpers/__init__.py
pymeshup/gui/helpers/vtkBlenderLikeInteractionStyle.py
pymeshup/helpers/__init__.py
pymeshup/helpers/darkmode.py
pymeshup/helpers/earcut_2d.py
pymeshup/helpers/geo_math.py
pymeshup/helpers/triangulate_non_convex.py
pymeshup/resources/pymeshup_logo.ico
pymeshup/resources/pymeshup_logo.png
pymeshup/syntaxedit/__init__.py
pymeshup/syntaxedit/core.py
pymeshup/syntaxedit/highlightslot.py
pymeshup-25.10.17.dist-info/licenses/AUTHORS.md
pymeshup-25.10.17.dist-info/licenses/LICENSE.txt
pymeshup-25.10.17.dist-info/METADATA
pymeshup-25.10.17.dist-info/WHEEL
pymeshup-25.10.17.dist-info/entry_points.txt
pymeshup-25.10.17.dist-info/top_level.txt
pymeshup-25.10.17.dist-info/RECORD
