Metadata-Version: 2.4
Name: pymeshup
Version: 25.10.17
Summary: Make volume meshes the easy way
Author-email: Ruben de Bruin <rubendebruin@gmail.com>
License-Expression: MPL-2.0
Project-URL: Documentation, https://open-ocean.org/
Keywords: meshing,volume,geometry
Classifier: Development Status :: 4 - Beta
Classifier: Programming Language :: Python :: 3
Classifier: Operating System :: OS Independent
Requires-Python: <=3.13,>=3.8
License-File: LICENSE.txt
License-File: AUTHORS.md
Requires-Dist: vedo
Requires-Dist: vtk<9.5,>=9.3
Requires-Dist: numpy
Requires-Dist: matplotlib
Requires-Dist: PySide6-Essentials
Requires-Dist: pymeshlab
Requires-Dist: capytaine>=2.2
Requires-Dist: mafredo
Requires-Dist: cadquery
Requires-Dist: netcdf4>=1.7.2
Provides-Extra: testing
Requires-Dist: setuptools; extra == "testing"
Requires-Dist: pytest; extra == "testing"
Provides-Extra: exe
Requires-Dist: pyinstaller; extra == "exe"
Dynamic: license-file
